Workbook

Sheet MAPPATURA
A1: MAPPATURA DELLE VOCI DI CONTO SUL CASH FLOW
A2: Fonte di verita' della riclassificazione. Un movimento si registra sempre sulla voce di dettaglio: famiglia e sottogruppo sono derivati, mai scelti a mano.
A4: Codice | B4: Sezione | C4: Mastro | D4: Gruppo | E4: Voce di conto | F4: Famiglia | G4: Sottogruppo | H4: Nome sottogruppo | I4: Segno | J4: Cassa | K4: Regola centro di costo | L4: Note
A5: 10.01 | B5: RICAVI | C5: 10 - Ricavi delle vendite e delle prestazioni | E5: Corrispettivi | F5: A | G5: A1 | H5: Corrispettivi | I5: Entrata | J5: SI | K5: Obbligatorio
A6: 10.09 | B6: RICAVI | C6: 10 - Ricavi delle vendite e delle prestazioni | E6: Resi, sconti e abbuoni su vendite | F6: A | G6: A1 | H6: Corrispettivi | I6: Rettifica | J6: SI | K6: Obbligatorio | L6: Segno negativo: rettifica dei ricavi
A7: 11.01 | B7: RICAVI | C7: 11 - Ricavi eventi | E7: Ricavi eventi serali (ingressi e consumazioni) | F7: A | G7: A2 | H7: Eventi | I7: Entrata | J7: SI | K7: Obbligatorio
A8: 11.02 | B8: RICAVI | C8: 11 - Ricavi eventi | E8: Ricavi eventi privati e compleanni | F8: A | G8: A2 | H8: Eventi | I8: Entrata | J8: SI | K8: Obbligatorio
A9: 12.01 | B9: RICAVI | C9: 12 - Altri ricavi e proventi | E9: Proventi vari | F9: A | G9: A3 | H9: Altri proventi | I9: Entrata | J9: SI | K9: Default STR
A10: 12.02 | B10: RICAVI | C10: 12 - Altri ricavi e proventi | E10: Contributi in conto esercizio | F10: A | G10: A3 | H10: Altri proventi | I10: Entrata | J10: SI | K10: Default STR
A11: 12.03 | B11: RICAVI | C11: 12 - Altri ricavi e proventi | E11: Rimborsi assicurativi | F11: A | G11: A3 | H11: Altri proventi | I11: Entrata | J11: SI | K11: Default STR
A12: 12.04 | B12: RICAVI | C12: 12 - Altri ricavi e proventi | E12: Premi, bonus e contributi da fornitori | F12: A | G12: A3 | H12: Altri proventi | I12: Entrata | J12: SI | K12: Default STR
A13: 12.06 | B13: RICAVI | C13: 12 - Altri ricavi e proventi | E13: Sopravvenienze attive | F13: A | G13: A3 | H13: Altri proventi | I13: Entrata | J13: SI | K13: Default STR
A14: 12.07 | B14: RICAVI | C14: 12 - Altri ricavi e proventi | E14: Plusvalenze da alienazione cespiti | I14: - | J14: NO | K14: Default STR | L14: Fuori cash flow: Plusvalenza contabile; l'incasso della cessione e' 40.1.04
A15: 13.01 | B15: RICAVI | C15: 13 - Proventi finanziari | E15: Interessi attivi bancari | F15: A | G15: A3 | H15: Altri proventi | I15: Entrata | J15: SI | K15: Default STR
A16: 13.02 | B16: RICAVI | C16: 13 - Proventi finanziari | E16: Altri proventi finanziari | F16: A | G16: A3 | H16: Altri proventi | I16: Entrata | J16: SI | K16: Default STR
A17: 20.1.01 | B17: COSTI | C17: 20 - Materie prime, sussidiarie e merci | D17: 20.1 - Beverage alcolico | E17: Birra fusto | F17: B | G17: B1 | H17: Beverage alcolico | I17: Uscita | J17: SI | K17: Obbligatorio
A18: 20.1.02 | B18: COSTI | C18: 20 - Materie prime, sussidiarie e merci | D18: 20.1 - Beverage alcolico | E18: Birra bottiglia e lattina | F18: B | G18: B1 | H18: Beverage alcolico | I18: Uscita | J18: SI | K18: Obbligatorio
A19: 20.1.03 | B19: COSTI | C19: 20 - Materie prime, sussidiarie e merci | D19: 20.1 - Beverage alcolico | E19: Distillati e liquori | F19: B | G19: B1 | H19: Beverage alcolico | I19: Uscita | J19: SI | K19: Obbligatorio
A20: 20.1.04 | B20: COSTI | C20: 20 - Materie prime, sussidiarie e merci | D20: 20.1 - Beverage alcolico | E20: Vermouth, bitter e aperitivi | F20: B | G20: B1 | H20: Beverage alcolico | I20: Uscita | J20: SI | K20: Obbligatorio
A21: 20.1.05 | B21: COSTI | C21: 20 - Materie prime, sussidiarie e merci | D21: 20.1 - Beverage alcolico | E21: Vini | F21: B | G21: B1 | H21: Beverage alcolico | I21: Uscita | J21: SI | K21: Obbligatorio
A22: 20.2.01 | B22: COSTI | C22: 20 - Materie prime, sussidiarie e merci | D22: 20.2 - Beverage analcolico | E22: Bibite e soft drink | F22: B | G22: B2 | H22: Beverage analcolico | I22: Uscita | J22: SI | K22: Obbligatorio
A23: 20.2.02 | B23: COSTI | C23: 20 - Materie prime, sussidiarie e merci | D23: 20.2 - Beverage analcolico | E23: Acqua minerale | F23: B | G23: B2 | H23: Beverage analcolico | I23: Uscita | J23: SI | K23: Obbligatorio
A24: 20.2.03 | B24: COSTI | C24: 20 - Materie prime, sussidiarie e merci | D24: 20.2 - Beverage analcolico | E24: Succhi, nettari e centrifugati | F24: B | G24: B2 | H24: Beverage analcolico | I24: Uscita | J24: SI | K24: Obbligatorio
A25: 20.2.04 | B25: COSTI | C25: 20 - Materie prime, sussidiarie e merci | D25: 20.2 - Beverage analcolico | E25: Sciroppi, purea e mixer | F25: B | G25: B2 | H25: Beverage analcolico | I25: Uscita | J25: SI | K25: Obbligatorio
A26: 20.3.01 | B26: COSTI | C26: 20 - Materie prime, sussidiarie e merci | D26: 20.3 - Caffetteria | E26: Caffè | F26: B | G26: B3 | H26: Caffetteria | I26: Uscita | J26: SI | K26: Obbligatorio
A27: 20.3.02 | B27: COSTI | C27: 20 - Materie prime, sussidiarie e merci | D27: 20.3 - Caffetteria | E27: Latte e derivati | F27: B | G27: B3 | H27: Caffetteria | I27: Uscita | J27: SI | K27: Obbligatorio
A28: 20.3.03 | B28: COSTI | C28: 20 - Materie prime, sussidiarie e merci | D28: 20.3 - Caffetteria | E28: Tè, infusi e cioccolata | F28: B | G28: B3 | H28: Caffetteria | I28: Uscita | J28: SI | K28: Obbligatorio
... A39: 20.5.05 | B39: COSTI | C39: 20 - Materie prime, sussidiarie e merci | D39: 20.5 - Consumabili di servizio | E39: Altri materiali di consumo | F39: B | G39: B5 | H39: Consumabili di servizio | I39: Uscita | J39: SI | K39: Obbligatorio
A40: 20.6.01 | B40: COSTI | C40: 20 - Materie prime, sussidiarie e merci | D40: 20.6 - Rettifiche e variazioni | E40: Resi, sconti e premi su acquisti | F40: B | G40: B6 | H40: Rettifiche su acquisti | I40: Rettifica | J40: SI | K40: Obbligatorio | L40: Segno negativo: rettifica dei costi
A41: 20.6.02 | B41: COSTI | C41: 20 - Materie prime, sussidiarie e merci | D41: 20.6 - Rettifiche e variazioni | E41: Rimanenze iniziali | I41: - | J41: NO | K41: Obbligatorio | L41: Fuori cash flow: Variazione di magazzino
A42: 20.6.03 | B42: COSTI | C42: 20 - Materie prime, sussidiarie e merci | D42: 20.6 - Rettifiche e variazioni | E42: Rimanenze finali | I42: - | J42: NO | K42: Obbligatorio | L42: Segno negativo: riduce il consumo | Fuori cash flow: Variazione di magazzino
A43: 20.6.04 | B43: COSTI | C43: 20 - Materie prime, sussidiarie e merci | D43: 20.6 - Rettifiche e variazioni | E43: Ammanchi, rotture e cali | I43: - | J43: NO | K43: Obbligatorio | L43: Fuori cash flow: Riclassifica di valore, nessun esborso
A44: 20.6.05 | B44: COSTI | C44: 20 - Materie prime, sussidiarie e merci | D44: 20.6 - Rettifiche e variazioni | E44: Omaggi, autoconsumo e staff meal | I44: - | J44: NO | K44: Obbligatorio | L44: Fuori cash flow: Riclassifica di valore, nessun esborso
A45: 21.01 | B45: COSTI | C45: 21 - Attrezzatura e beni strumentali minuti | E45: Vetreria e attrezzatura bar | F45: E | G45: E5 | H45: Attrezzatura e allestimenti | I45: Uscita | J45: SI | K45: Obbligatorio
A46: 21.02 | B46: COSTI | C46: 21 - Attrezzatura e beni strumentali minuti | E46: Stoviglie, posateria e complementi sala | F46: E | G46: E5 | H46: Attrezzatura e allestimenti | I46: Uscita | J46: SI | K46: Obbligatorio
A47: 21.03 | B47: COSTI | C47: 21 - Attrezzatura e beni strumentali minuti | E47: Piccola attrezzatura cucina | F47: E | G47: E5 | H47: Attrezzatura e allestimenti | I47: Uscita | J47: SI | K47: Obbligatorio
A48: 21.04 | B48: COSTI | C48: 21 - Attrezzatura e beni strumentali minuti | E48: Beni strumentali < 516,46 EUR | F48: E | G48: E5 | H48: Attrezzatura e allestimenti | I48: Uscita | J48: SI | K48: Obbligatorio | L48: Deducibili al 100% nell'esercizio
A49: 21.05 | B49: COSTI | C49: 21 - Attrezzatura e beni strumentali minuti | E49: Arredi e complementi minuti | F49: E | G49: E5 | H49: Attrezzatura e allestimenti | I49: Uscita | J49: SI | K49: Obbligatorio
A50: 21.06 | B50: COSTI | C50: 21 - Attrezzatura e beni strumentali minuti | E50: Divise e abbigliamento personale | F50: E | G50: E5 | H50: Attrezzatura e allestimenti | I50: Uscita | J50: SI | K50: Obbligatorio
A51: 21.07 | B51: COSTI | C51: 21 - Attrezzatura e beni strumentali minuti | E51: Allestimenti, fiori e decorazioni locale | F51: E | G51: E5 | H51: Attrezzatura e allestimenti | I51: Uscita | J51: SI | K51: Obbligatorio | L51: Decorazioni ordinarie del locale (non evento)
A52: 22.01 | B52: COSTI | C52: 22 - Utenze | E52: Energia elettrica | F52: E | G52: E2 | H52: Utenze | I52: Uscita | J52: SI | K52: Obbligatorio
A53: 22.02 | B53: COSTI | C53: 22 - Utenze | E53: Gas da rete (metano) | F53: E | G53: E2 | H53: Utenze | I53: Uscita | J53: SI | K53: Obbligatorio | L53: Fornitura da impianto/contatore; di fatto solo Villa Varda
A54: 22.03 | B54: COSTI | C54: 22 - Utenze | E54: Acqua | F54: E | G54: E2 | H54: Utenze | I54: Uscita | J54: SI | K54: Obbligatorio
A55: 22.04 | B55: COSTI | C55: 22 - Utenze | E55: Telefonia e connettività | F55: E | G55: E2 | H55: Utenze | I55: Uscita | J55: SI | K55: Obbligatorio
A56: 22.05 | B56: COSTI | C56: 22 - Utenze | E56: Rifiuti - TARI e servizio smaltimento | F56: E | G56: E2 | H56: Utenze | I56: Uscita | J56: SI | K56: Obbligatorio
A57: 22.07 | B57: COSTI | C57: 22 - Utenze | E57: Bombole di gas (GPL) | F57: E | G57: E2 | H57: Utenze | I57: Uscita | J57: SI | K57: Obbligatorio | L57: Acquisto ricariche; di fatto solo Casetta
A58: 23.01 | B58: COSTI | C58: 23 - Servizi operativi | E58: Manutenzioni e riparazioni | F58: E | G58: E4 | H58: Manutenzioni e servizi operativi | I58: Uscita | J58: SI | K58: Obbligatorio
A59: 23.02 | B59: COSTI | C59: 23 - Servizi operativi | E59: Contratti di manutenzione a canone | F59: E | G59: E4 | H59: Manutenzioni e servizi operativi | I59: Uscita | J59: SI | K59: Obbligatorio
A60: 23.03 | B60: COSTI | C60: 23 - Servizi operativi | E60: Servizi di pulizia esterni | F60: E | G60: E4 | H60: Manutenzioni e servizi operativi | I60: Uscita | J60: SI | K60: Obbligatorio
A61: 23.05 | B61: COSTI | C61: 23 - Servizi operativi | E61: Vigilanza e servizi di sicurezza | F61: E | G61: E4 | H61: Manutenzioni e servizi operativi | I61: Uscita | J61: SI | K61: Obbligatorio
A62: 23.07 | B62: COSTI | C62: 23 - Servizi operativi | E62: Disinfestazione e derattizzazione | F62: E | G62: E4 | H62: Manutenzioni e servizi operativi | I62: Uscita | J62: SI | K62: Obbligatorio
A63: 24.01 | B63: COSTI | C63: 24 - Servizi professionali e amministrativi | E63: Consulenza contabile, fiscale e dichiarazioni | F63: E | G63: E6 | H63: Servizi professionali e amministrativi | I63: Uscita | J63: SI | K63: Default STR
A64: 24.02 | B64: COSTI | C64: 24 - Servizi professionali e amministrativi | E64: Servizi elaborazione paghe | F64: E | G64: E6 | H64: Servizi professionali e amministrativi | I64: Uscita | J64: SI | K64: Default STR
A65: 24.03 | B65: COSTI | C65: 24 - Servizi professionali e amministrativi | E65: Consulenze legali | F65: E | G65: E6 | H65: Servizi professionali e amministrativi | I65: Uscita | J65: SI | K65: Default STR
A66: 24.04 | B66: COSTI | C66: 24 - Servizi professionali e amministrativi | E66: Consulenze tecniche e progettazione | F66: E | G66: E6 | H66: Servizi professionali e amministrativi | I66: Uscita | J66: SI | K66: Default STR
A67: 24.05 | B67: COSTI | C67: 24 - Servizi professionali e amministrativi | E67: Consulenza del lavoro e sicurezza (D.Lgs. 81/08) | F67: E | G67: E6 | H67: Servizi professionali e amministrativi | I67: Uscita | J67: SI | K67: Default STR
A68: 24.06 | B68: COSTI | C68: 24 - Servizi professionali e amministrativi | E68: Medico competente e sorveglianza sanitaria | F68: E | G68: E6 | H68: Servizi professionali e amministrativi | I68: Uscita | J68: SI | K68: Default STR
A69: 24.07 | B69: COSTI | C69: 24 - Servizi professionali e amministrativi | E69: Formazione, HACCP e certificazioni | F69: E | G69: E6 | H69: Servizi professionali e amministrativi | I69: Uscita | J69: SI | K69: Default STR
... A98: 27.08 | B98: COSTI | C98: 27 - Godimento beni di terzi | E98: Royalties e diritti d'uso marchio | F98: E | G98: E3 | H98: Noleggi, leasing e licenze | I98: Uscita | J98: SI | K98: Obbligatorio
A99: 28.1.01 | B99: COSTI | C99: 28 - Costo del personale | D99: 28.1 - Retribuzioni | E99: Retribuzioni personale dipendente serale | F99: C | G99: C1 | H99: Retribuzioni | I99: Uscita | J99: SI | K99: Obbligatorio
A100: 28.1.02 | B100: COSTI | C100: 28 - Costo del personale | D100: 28.1 - Retribuzioni | E100: Retribuzioni personale extra e a chiamata | F100: C | G100: C1 | H100: Retribuzioni | I100: Uscita | J100: SI | K100: Obbligatorio
A101: 28.1.03 | B101: COSTI | C101: 28 - Costo del personale | D101: 28.1 - Retribuzioni | E101: Retribuzioni personale servizio mattina | F101: C | G101: C1 | H101: Retribuzioni | I101: Uscita | J101: SI | K101: Obbligatorio
A102: 28.1.04 | B102: COSTI | C102: 28 - Costo del personale | D102: 28.1 - Retribuzioni | E102: Retribuzioni personale extra mattina | F102: C | G102: C1 | H102: Retribuzioni | I102: Uscita | J102: SI | K102: Obbligatorio
A103: 28.1.05 | B103: COSTI | C103: 28 - Costo del personale | D103: 28.1 - Retribuzioni | E103: Retribuzioni personale pulizie | F103: C | G103: C1 | H103: Retribuzioni | I103: Uscita | J103: SI | K103: Obbligatorio
A104: 28.1.06 | B104: COSTI | C104: 28 - Costo del personale | D104: 28.1 - Retribuzioni | E104: Retribuzioni personale sicurezza | F104: C | G104: C1 | H104: Retribuzioni | I104: Uscita | J104: SI | K104: Obbligatorio
A105: 28.1.07 | B105: COSTI | C105: 28 - Costo del personale | D105: 28.1 - Retribuzioni | E105: Straordinari e maggiorazioni | F105: C | G105: C1 | H105: Retribuzioni | I105: Uscita | J105: SI | K105: Obbligatorio
A106: 28.1.08 | B106: COSTI | C106: 28 - Costo del personale | D106: 28.1 - Retribuzioni | E106: Ferie, permessi e mensilità aggiuntive | F106: C | G106: C1 | H106: Retribuzioni | I106: Uscita | J106: SI | K106: Obbligatorio
A107: 28.1.09 | B107: COSTI | C107: 28 - Costo del personale | D107: 28.1 - Retribuzioni | E107: Retribuzioni personale amministrativo | F107: C | G107: C1 | H107: Retribuzioni | I107: Uscita | J107: SI | K107: Default STR | L107: Ex voce 'Retribuzione del personale - UFFICIO'
A108: 28.2.01 | B108: COSTI | C108: 28 - Costo del personale | D108: 28.2 - Oneri sociali | E108: Contributi INPS c/azienda | F108: C | G108: C2 | H108: Oneri sociali | I108: Uscita | J108: SI | K108: Obbligatorio
A109: 28.2.02 | B109: COSTI | C109: 28 - Costo del personale | D109: 28.2 - Oneri sociali | E109: Contributi INAIL | F109: C | G109: C2 | H109: Oneri sociali | I109: Uscita | J109: SI | K109: Obbligatorio
A110: 28.2.03 | B110: COSTI | C110: 28 - Costo del personale | D110: 28.2 - Oneri sociali | E110: Fondi integrativi ed enti bilaterali | F110: C | G110: C2 | H110: Oneri sociali | I110: Uscita | J110: SI | K110: Obbligatorio
A111: 28.3.01 | B111: COSTI | C111: 28 - Costo del personale | D111: 28.3 - Accantonamenti | E111: Accantonamento TFR di competenza | I111: - | J111: NO | K111: Obbligatorio | L111: Fuori cash flow: Competenza; l'esborso e' 28.3.02
A112: 28.3.02 | B112: COSTI | C112: 28 - Costo del personale | D112: 28.3 - Accantonamenti | E112: TFR corrisposto nell'anno | F112: C | G112: C3 | H112: TFR corrisposto | I112: Uscita | J112: SI | K112: Obbligatorio | L112: Utilizzo del fondo: uscita finanziaria, non costo di competenza
A113: 28.4.01 | B113: COSTI | C113: 28 - Costo del personale | D113: 28.4 - Altri costi del personale | E113: Rimborsi spese dipendenti | F113: C | G113: C4 | H113: Altri costi del personale | I113: Uscita | J113: SI | K113: Obbligatorio
A114: 28.4.02 | B114: COSTI | C114: 28 - Costo del personale | D114: 28.4 - Altri costi del personale | E114: Welfare aziendale e fringe benefit | F114: C | G114: C4 | H114: Altri costi del personale | I114: Uscita | J114: SI | K114: Obbligatorio
A115: 28.4.03 | B115: COSTI | C115: 28 - Costo del personale | D115: 28.4 - Altri costi del personale | E115: Buoni pasto, vitto e alloggio | F115: C | G115: C4 | H115: Altri costi del personale | I115: Uscita | J115: SI | K115: Obbligatorio
A116: 28.4.04 | B116: COSTI | C116: 28 - Costo del personale | D116: 28.4 - Altri costi del personale | E116: Ricerca, selezione e tirocini | F116: C | G116: C4 | H116: Altri costi del personale | I116: Uscita | J116: SI | K116: Obbligatorio
A117: 28.4.05 | B117: COSTI | C117: 28 - Costo del personale | D117: 28.4 - Altri costi del personale | E117: Altri costi per personale dipendente | F117: C | G117: C4 | H117: Altri costi del personale | I117: Uscita | J117: SI | K117: Obbligatorio
A118: 29.01 | B118: COSTI | C118: 29 - Organi sociali e collaborazioni | E118: Compenso amministratore | F118: C | G118: C5 | H118: Organi sociali e collaborazioni | I118: Uscita | J118: SI | K118: Default STR
A119: 29.02 | B119: COSTI | C119: 29 - Organi sociali e collaborazioni | E119: Contributi INPS gestione separata amministratore | F119: C | G119: C5 | H119: Organi sociali e collaborazioni | I119: Uscita | J119: SI | K119: Default STR
A120: 29.04 | B120: COSTI | C120: 29 - Organi sociali e collaborazioni | E120: Rimborsi spese amministratore | F120: C | G120: C5 | H120: Organi sociali e collaborazioni | I120: Uscita | J120: SI | K120: Default STR
A121: 29.05 | B121: COSTI | C121: 29 - Organi sociali e collaborazioni | E121: Compensi per collaborazioni e prestazioni occasionali | F121: C | G121: C5 | H121: Organi sociali e collaborazioni | I121: Uscita | J121: SI | K121: Default STR
A122: 30.01 | B122: COSTI | C122: 30 - Oneri diversi di gestione | E122: Imposta di bollo | F122: E | G122: E8 | H122: Tributi, assicurazioni e oneri diversi | I122: Uscita | J122: SI | K122: Default STR
A123: 30.02 | B123: COSTI | C123: 30 - Oneri diversi di gestione | E123: Tassa annuale vidimazione libri sociali | F123: E | G123: E8 | H123: Tributi, assicurazioni e oneri diversi | I123: Uscita | J123: SI | K123: Default STR
A124: 30.03 | B124: COSTI | C124: 30 - Oneri diversi di gestione | E124: Diritti camerali, catastali e vari | F124: E | G124: E8 | H124: Tributi, assicurazioni e oneri diversi | I124: Uscita | J124: SI | K124: Default STR
A125: 30.04 | B125: COSTI | C125: 30 - Oneri diversi di gestione | E125: Imposte comunali sugli immobili (IMU / ILIA) | F125: E | G125: E8 | H125: Tributi, assicurazioni e oneri diversi | I125: Uscita | J125: SI | K125: Obbligatorio
A126: 30.05 | B126: COSTI | C126: 30 - Oneri diversi di gestione | E126: Occupazione suolo pubblico (COSAP / CUP) | F126: E | G126: E8 | H126: Tributi, assicurazioni e oneri diversi | I126: Uscita | J126: SI | K126: Obbligatorio
A127: 30.06 | B127: COSTI | C127: 30 - Oneri diversi di gestione | E127: Abbonamenti, riviste e pubblicazioni | F127: E | G127: E8 | H127: Tributi, assicurazioni e oneri diversi | I127: Uscita | J127: SI | K127: Default STR
A128: 30.07 | B128: COSTI | C128: 30 - Oneri diversi di gestione | E128: Quote associative di categoria | F128: E | G128: E8 | H128: Tributi, assicurazioni e oneri diversi | I128: Uscita | J128: SI | K128: Default STR
A129: 30.08 | B129: COSTI | C129: 30 - Oneri diversi di gestione | E129: Assicurazioni | F129: E | G129: E8 | H129: Tributi, assicurazioni e oneri diversi | I129: Uscita | J129: SI | K129: Obbligatorio
A130: 30.09 | B130: COSTI | C130: 30 - Oneri diversi di gestione | E130: Sanzioni tributarie, previdenziali e penalità | F130: E | G130: E8 | H130: Tributi, assicurazioni e oneri diversi | I130: Uscita | J130: SI | K130: Default STR | L130: Costo indeducibile
A131: 30.10 | B131: COSTI | C131: 30 - Oneri diversi di gestione | E131: Sopravvenienze passive | F131: E | G131: E8 | H131: Tributi, assicurazioni e oneri diversi | I131: Uscita | J131: SI | K131: Default STR
A132: 30.11 | B132: COSTI | C132: 30 - Oneri diversi di gestione | E132: Perdite su crediti | I132: - | J132: NO | K132: Default STR | L132: Fuori cash flow: Mancata entrata, non un'uscita
A133: 30.12 | B133: COSTI | C133: 30 - Oneri diversi di gestione | E133: Minusvalenze da alienazione cespiti | I133: - | J133: NO | K133: Default STR | L133: Fuori cash flow: Minusvalenza contabile
A134: 30.13 | B134: COSTI | C134: 30 - Oneri diversi di gestione | E134: Altri oneri di gestione | F134: E | G134: E8 | H134: Tributi, assicurazioni e oneri diversi | I134: Uscita | J134: SI | K134: Default STR
A135: 30.14 | B135: COSTI | C135: 30 - Oneri diversi di gestione | E135: SIAE e SCF musica d'ambiente | F135: E | G135: E8 | H135: Tributi, assicurazioni e oneri diversi | I135: Uscita | J135: SI | K135: Obbligatorio | L135: Abbonamento annuale filodiffusione; la SIAE degli eventi resta in 26.09
A136: 30.15 | B136: COSTI | C136: 30 - Oneri diversi di gestione | E136: Differenze e ammanchi di cassa | F136: E | G136: E8 | H136: Tributi, assicurazioni e oneri diversi | I136: Uscita | J136: SI | K136: Obbligatorio | L136: Differenze tra fondo cassa teorico e contato
A137: 31.01 | B137: COSTI | C137: 31 - Ammortamenti e svalutazioni | E137: Ammortamento immobilizzazioni immateriali | I137: - | J137: NO | K137: Obbligatorio | L137: Fuori cash flow: Non tocca il conto
A138: 31.02 | B138: COSTI | C138: 31 - Ammortamenti e svalutazioni | E138: Ammortamento migliorie su beni di terzi | I138: - | J138: NO | K138: Obbligatorio | L138: Fuori cash flow: Non tocca il conto
A139: 31.03 | B139: COSTI | C139: 31 - Ammortamenti e svalutazioni | E139: Ammortamento impianti e macchinari | I139: - | J139: NO | K139: Obbligatorio | L139: Fuori cash flow: Non tocca il conto
...

Sheet CASH FLOW
A1: CASH FLOW — consuntivo
A2: Solo movimenti che toccano cassa o banca. Entrate positive, uscite negative. Le voci di dettaglio sono nascoste: usa i pulsanti + a sinistra per aprirle.
A4: Codice | B4: Voce | C4: GEN | D4: FEB | E4: MAR | F4: APR | G4: MAG | H4: GIU | I4: LUG | J4: AGO | K4: SET | L4: OTT | M4: NOV | N4: DIC | O4: TOTALE
A5: A | B5: INCASSI OPERATIVI | C5: =SUBTOTAL(9,C6:C19) | D5: =SUBTOTAL(9,D6:D19) | E5: =SUBTOTAL(9,E6:E19) | F5: =SUBTOTAL(9,F6:F19) | G5: =SUBTOTAL(9,G6:G19) | H5: =SUBTOTAL(9,H6:H19) | I5: =SUBTOTAL(9,I6:I19) | J5: =SUBTOTAL(9,J6:J19) | ... O5: =SUBTOTAL(9,O6:O19)
A6: A1 | B6: Corrispettivi | C6: =SUBTOTAL(9,C7:C8) | D6: =SUBTOTAL(9,D7:D8) | E6: =SUBTOTAL(9,E7:E8) | F6: =SUBTOTAL(9,F7:F8) | G6: =SUBTOTAL(9,G7:G8) | H6: =SUBTOTAL(9,H7:H8) | I6: =SUBTOTAL(9,I7:I8) | J6: =SUBTOTAL(9,J7:J8) | ... O6: =SUBTOTAL(9,O7:O8)
A7: 10.01 | B7: Corrispettivi | O7: =SUM(C7:N7)
A8: 10.09 | B8: Resi, sconti e abbuoni su vendite | O8: =SUM(C8:N8)
A9: A2 | B9: Eventi | C9: =SUBTOTAL(9,C10:C11) | D9: =SUBTOTAL(9,D10:D11) | E9: =SUBTOTAL(9,E10:E11) | F9: =SUBTOTAL(9,F10:F11) | G9: =SUBTOTAL(9,G10:G11) | H9: =SUBTOTAL(9,H10:H11) | I9: =SUBTOTAL(9,I10:I11) | J9: =SUBTOTAL(9,J10:J11) | ... O9: =SUBTOTAL(9,O10:O11)
A10: 11.01 | B10: Ricavi eventi serali (ingressi e consumazioni) | O10: =SUM(C10:N10)
A11: 11.02 | B11: Ricavi eventi privati e compleanni | O11: =SUM(C11:N11)
A12: A3 | B12: Altri proventi | C12: =SUBTOTAL(9,C13:C19) | D12: =SUBTOTAL(9,D13:D19) | E12: =SUBTOTAL(9,E13:E19) | F12: =SUBTOTAL(9,F13:F19) | G12: =SUBTOTAL(9,G13:G19) | H12: =SUBTOTAL(9,H13:H19) | I12: =SUBTOTAL(9,I13:I19) | J12: =SUBTOTAL(9,J13:J19) | ... O12: =SUBTOTAL(9,O13:O19)
A13: 12.01 | B13: Proventi vari | O13: =SUM(C13:N13)
A14: 12.02 | B14: Contributi in conto esercizio | O14: =SUM(C14:N14)
A15: 12.03 | B15: Rimborsi assicurativi | O15: =SUM(C15:N15)
A16: 12.04 | B16: Premi, bonus e contributi da fornitori | O16: =SUM(C16:N16)
A17: 12.06 | B17: Sopravvenienze attive | O17: =SUM(C17:N17)
A18: 13.01 | B18: Interessi attivi bancari | O18: =SUM(C18:N18)
A19: 13.02 | B19: Altri proventi finanziari | O19: =SUM(C19:N19)
A21: B | B21: COSTO DEL VENDUTO | C21: =SUBTOTAL(9,C22:C51) | D21: =SUBTOTAL(9,D22:D51) | E21: =SUBTOTAL(9,E22:E51) | F21: =SUBTOTAL(9,F22:F51) | G21: =SUBTOTAL(9,G22:G51) | H21: =SUBTOTAL(9,H22:H51) | I21: =SUBTOTAL(9,I22:I51) | J21: =SUBTOTAL(9,J22:J51) | ... O21: =SUBTOTAL(9,O22:O51)
A22: B1 | B22: Beverage alcolico | C22: =SUBTOTAL(9,C23:C27) | D22: =SUBTOTAL(9,D23:D27) | E22: =SUBTOTAL(9,E23:E27) | F22: =SUBTOTAL(9,F23:F27) | G22: =SUBTOTAL(9,G23:G27) | H22: =SUBTOTAL(9,H23:H27) | I22: =SUBTOTAL(9,I23:I27) | J22: =SUBTOTAL(9,J23:J27) | ... O22: =SUBTOTAL(9,O23:O27)
A23: 20.1.01 | B23: Birra fusto | O23: =SUM(C23:N23)
A24: 20.1.02 | B24: Birra bottiglia e lattina | O24: =SUM(C24:N24)
A25: 20.1.03 | B25: Distillati e liquori | O25: =SUM(C25:N25)
A26: 20.1.04 | B26: Vermouth, bitter e aperitivi | O26: =SUM(C26:N26)
A27: 20.1.05 | B27: Vini | O27: =SUM(C27:N27)
A28: B2 | B28: Beverage analcolico | C28: =SUBTOTAL(9,C29:C32) | D28: =SUBTOTAL(9,D29:D32) | E28: =SUBTOTAL(9,E29:E32) | F28: =SUBTOTAL(9,F29:F32) | G28: =SUBTOTAL(9,G29:G32) | H28: =SUBTOTAL(9,H29:H32) | I28: =SUBTOTAL(9,I29:I32) | J28: =SUBTOTAL(9,J29:J32) | ... O28: =SUBTOTAL(9,O29:O32)
A29: 20.2.01 | B29: Bibite e soft drink | O29: =SUM(C29:N29)
A30: 20.2.02 | B30: Acqua minerale | O30: =SUM(C30:N30)
A31: 20.2.03 | B31: Succhi, nettari e centrifugati | O31: =SUM(C31:N31)
A32: 20.2.04 | B32: Sciroppi, purea e mixer | O32: =SUM(C32:N32)
A33: B3 | B33: Caffetteria | C33: =SUBTOTAL(9,C34:C37) | D33: =SUBTOTAL(9,D34:D37) | E33: =SUBTOTAL(9,E34:E37) | F33: =SUBTOTAL(9,F34:F37) | G33: =SUBTOTAL(9,G34:G37) | H33: =SUBTOTAL(9,H34:H37) | I33: =SUBTOTAL(9,I34:I37) | J33: =SUBTOTAL(9,J34:J37) | ... O33: =SUBTOTAL(9,O34:O37)
A34: 20.3.01 | B34: Caffè | O34: =SUM(C34:N34)
A35: 20.3.02 | B35: Latte e derivati | O35: =SUM(C35:N35)
A36: 20.3.03 | B36: Tè, infusi e cioccolata | O36: =SUM(C36:N36)
A37: 20.3.04 | B37: Zucchero e complementi caffetteria | O37: =SUM(C37:N37)
A38: B4 | B38: Food | C38: =SUBTOTAL(9,C39:C43) | D38: =SUBTOTAL(9,D39:D43) | E38: =SUBTOTAL(9,E39:E43) | F38: =SUBTOTAL(9,F39:F43) | G38: =SUBTOTAL(9,G39:G43) | H38: =SUBTOTAL(9,H39:H43) | I38: =SUBTOTAL(9,I39:I43) | J38: =SUBTOTAL(9,J39:J43) | ... O38: =SUBTOTAL(9,O39:O43)
A39: 20.4.01 | B39: Beni alimentari e gastronomia | O39: =SUM(C39:N39)
A40: 20.4.02 | B40: Frutta e verdura | O40: =SUM(C40:N40)
A41: 20.4.03 | B41: Pane e prodotti da forno | O41: =SUM(C41:N41)
A42: 20.4.04 | B42: Pasticceria e dolci | O42: =SUM(C42:N42)
A43: 20.4.05 | B43: Snack e prodotti confezionati | O43: =SUM(C43:N43)
A44: B5 | B44: Consumabili di servizio | C44: =SUBTOTAL(9,C45:C49) | D44: =SUBTOTAL(9,D45:D49) | E44: =SUBTOTAL(9,E45:E49) | F44: =SUBTOTAL(9,F45:F49) | G44: =SUBTOTAL(9,G45:G49) | H44: =SUBTOTAL(9,H45:H49) | I44: =SUBTOTAL(9,I45:I49) | J44: =SUBTOTAL(9,J45:J49) | ... O44: =SUBTOTAL(9,O45:O49)
A45: 20.5.01 | B45: Ghiaccio | O45: =SUM(C45:N45)
A46: 20.5.02 | B46: Garnish e decorazioni | O46: =SUM(C46:N46)
A47: 20.5.03 | B47: Monouso, packaging e asporto | O47: =SUM(C47:N47)
A48: 20.5.04 | B48: Materiale igiene e pulizia | O48: =SUM(C48:N48)
A49: 20.5.05 | B49: Altri materiali di consumo | O49: =SUM(C49:N49)
A50: B6 | B50: Rettifiche su acquisti | C50: =SUBTOTAL(9,C51:C51) | D50: =SUBTOTAL(9,D51:D51) | E50: =SUBTOTAL(9,E51:E51) | F50: =SUBTOTAL(9,F51:F51) | G50: =SUBTOTAL(9,G51:G51) | H50: =SUBTOTAL(9,H51:H51) | I50: =SUBTOTAL(9,I51:I51) | J50: =SUBTOTAL(9,J51:J51) | ... O50: =SUBTOTAL(9,O51:O51)
A51: 20.6.01 | B51: Resi, sconti e premi su acquisti | O51: =SUM(C51:N51)
B52: MARGINE DI CONTRIBUZIONE | C52: =C5+C21 | D52: =D5+D21 | E52: =E5+E21 | F52: =F5+F21 | G52: =G5+G21 | H52: =H5+H21 | I52: =I5+I21 | J52: =J5+J21 | ... O52: =O5+O21
A54: C | B54: COSTO DEL PERSONALE | C54: =SUBTOTAL(9,C55:C81) | D54: =SUBTOTAL(9,D55:D81) | E54: =SUBTOTAL(9,E55:E81) | F54: =SUBTOTAL(9,F55:F81) | G54: =SUBTOTAL(9,G55:G81) | H54: =SUBTOTAL(9,H55:H81) | I54: =SUBTOTAL(9,I55:I81) | J54: =SUBTOTAL(9,J55:J81) | ... O54: =SUBTOTAL(9,O55:O81)
A55: C1 | B55: Retribuzioni | C55: =SUBTOTAL(9,C56:C64) | D55: =SUBTOTAL(9,D56:D64) | E55: =SUBTOTAL(9,E56:E64) | F55: =SUBTOTAL(9,F56:F64) | G55: =SUBTOTAL(9,G56:G64) | H55: =SUBTOTAL(9,H56:H64) | I55: =SUBTOTAL(9,I56:I64) | J55: =SUBTOTAL(9,J56:J64) | ... O55: =SUBTOTAL(9,O56:O64)
A56: 28.1.01 | B56: Retribuzioni personale dipendente serale | O56: =SUM(C56:N56)
A57: 28.1.02 | B57: Retribuzioni personale extra e a chiamata | O57: =SUM(C57:N57)
A58: 28.1.03 | B58: Retribuzioni personale servizio mattina | O58: =SUM(C58:N58)
A59: 28.1.04 | B59: Retribuzioni personale extra mattina | O59: =SUM(C59:N59)
A60: 28.1.05 | B60: Retribuzioni personale pulizie | O60: =SUM(C60:N60)
A61: 28.1.06 | B61: Retribuzioni personale sicurezza | O61: =SUM(C61:N61)
A62: 28.1.07 | B62: Straordinari e maggiorazioni | O62: =SUM(C62:N62)
A63: 28.1.08 | B63: Ferie, permessi e mensilità aggiuntive | O63: =SUM(C63:N63)
A64: 28.1.09 | B64: Retribuzioni personale amministrativo | O64: =SUM(C64:N64)
A65: C2 | B65: Oneri sociali | C65: =SUBTOTAL(9,C66:C68) | D65: =SUBTOTAL(9,D66:D68) | E65: =SUBTOTAL(9,E66:E68) | F65: =SUBTOTAL(9,F66:F68) | G65: =SUBTOTAL(9,G66:G68) | H65: =SUBTOTAL(9,H66:H68) | I65: =SUBTOTAL(9,I66:I68) | J65: =SUBTOTAL(9,J66:J68) | ... O65: =SUBTOTAL(9,O66:O68)
A66: 28.2.01 | B66: Contributi INPS c/azienda | O66: =SUM(C66:N66)
A67: 28.2.02 | B67: Contributi INAIL | O67: =SUM(C67:N67)
A68: 28.2.03 | B68: Fondi integrativi ed enti bilaterali | O68: =SUM(C68:N68)
A69: C3 | B69: TFR corrisposto | C69: =SUBTOTAL(9,C70:C70) | D69: =SUBTOTAL(9,D70:D70) | E69: =SUBTOTAL(9,E70:E70) | F69: =SUBTOTAL(9,F70:F70) | G69: =SUBTOTAL(9,G70:G70) | H69: =SUBTOTAL(9,H70:H70) | I69: =SUBTOTAL(9,I70:I70) | J69: =SUBTOTAL(9,J70:J70) | ... O69: =SUBTOTAL(9,O70:O70)
A70: 28.3.02 | B70: TFR corrisposto nell'anno | O70: =SUM(C70:N70)
A71: C4 | B71: Altri costi del personale | C71: =SUBTOTAL(9,C72:C76) | D71: =SUBTOTAL(9,D72:D76) | E71: =SUBTOTAL(9,E72:E76) | F71: =SUBTOTAL(9,F72:F76) | G71: =SUBTOTAL(9,G72:G76) | H71: =SUBTOTAL(9,H72:H76) | I71: =SUBTOTAL(9,I72:I76) | J71: =SUBTOTAL(9,J72:J76) | ... O71: =SUBTOTAL(9,O72:O76)
A72: 28.4.01 | B72: Rimborsi spese dipendenti | O72: =SUM(C72:N72)
A73: 28.4.02 | B73: Welfare aziendale e fringe benefit | O73: =SUM(C73:N73)
A74: 28.4.03 | B74: Buoni pasto, vitto e alloggio | O74: =SUM(C74:N74)
A75: 28.4.04 | B75: Ricerca, selezione e tirocini | O75: =SUM(C75:N75)
A76: 28.4.05 | B76: Altri costi per personale dipendente | O76: =SUM(C76:N76)
A77: C5 | B77: Organi sociali e collaborazioni | C77: =SUBTOTAL(9,C78:C81) | D77: =SUBTOTAL(9,D78:D81) | E77: =SUBTOTAL(9,E78:E81) | F77: =SUBTOTAL(9,F78:F81) | G77: =SUBTOTAL(9,G78:G81) | H77: =SUBTOTAL(9,H78:H81) | I77: =SUBTOTAL(9,I78:I81) | J77: =SUBTOTAL(9,J78:J81) | ... O77: =SUBTOTAL(9,O78:O81)
A78: 29.01 | B78: Compenso amministratore | O78: =SUM(C78:N78)
A79: 29.02 | B79: Contributi INPS gestione separata amministratore | O79: =SUM(C79:N79)
A80: 29.04 | B80: Rimborsi spese amministratore | O80: =SUM(C80:N80)
A81: 29.05 | B81: Compensi per collaborazioni e prestazioni occasionali | O81: =SUM(C81:N81)
A83: D | B83: COSTI DIRETTI EVENTI | C83: =SUBTOTAL(9,C84:C98) | D83: =SUBTOTAL(9,D84:D98) | E83: =SUBTOTAL(9,E84:E98) | F83: =SUBTOTAL(9,F84:F98) | G83: =SUBTOTAL(9,G84:G98) | H83: =SUBTOTAL(9,H84:H98) | I83: =SUBTOTAL(9,I84:I98) | J83: =SUBTOTAL(9,J84:J98) | ... O83: =SUBTOTAL(9,O84:O98)
A84: D1 | B84: Artisti e service | C84: =SUBTOTAL(9,C85:C86) | D84: =SUBTOTAL(9,D85:D86) | E84: =SUBTOTAL(9,E85:E86) | F84: =SUBTOTAL(9,F85:F86) | G84: =SUBTOTAL(9,G85:G86) | H84: =SUBTOTAL(9,H85:H86) | I84: =SUBTOTAL(9,I85:I86) | J84: =SUBTOTAL(9,J85:J86) | ... O84: =SUBTOTAL(9,O85:O86)
A85: 26.01 | B85: Artisti, DJ e compensi live | O85: =SUM(C85:N85)
A86: 26.02 | B86: Service audio-luci e noleggi tecnici | O86: =SUM(C86:N86)
A87: D2 | B87: Manodopera evento | C87: =SUBTOTAL(9,C88:C90) | D87: =SUBTOTAL(9,D88:D90) | E87: =SUBTOTAL(9,E88:E90) | F87: =SUBTOTAL(9,F88:F90) | G87: =SUBTOTAL(9,G88:G90) | H87: =SUBTOTAL(9,H88:H90) | I87: =SUBTOTAL(9,I88:I90) | J87: =SUBTOTAL(9,J88:J90) | ... O87: =SUBTOTAL(9,O88:O90)
A88: 26.03 | B88: Personale evento | O88: =SUM(C88:N88)
A89: 26.05 | B89: Sicurezza e steward evento | O89: =SUM(C89:N89)
A90: 26.06 | B90: Servizi di pulizia evento | O90: =SUM(C90:N90)
A91: D3 | B91: Promozione evento | C91: =SUBTOTAL(9,C92:C94) | D91: =SUBTOTAL(9,D92:D94) | E91: =SUBTOTAL(9,E92:E94) | F91: =SUBTOTAL(9,F92:F94) | G91: =SUBTOTAL(9,G92:G94) | H91: =SUBTOTAL(9,H92:H94) | I91: =SUBTOTAL(9,I92:I94) | J91: =SUBTOTAL(9,J92:J94) | ... O91: =SUBTOTAL(9,O92:O94)
A92: 26.04 | B92: PR e promoter evento | O92: =SUM(C92:N92)
A93: 26.07 | B93: Advertising e sponsorizzate evento | O93: =SUM(C93:N93)
A94: 26.08 | B94: Foto e grafiche evento | O94: =SUM(C94:N94)
A95: D4 | B95: Oneri e allestimenti evento | C95: =SUBTOTAL(9,C96:C98) | D95: =SUBTOTAL(9,D96:D98) | E95: =SUBTOTAL(9,E96:E98) | F95: =SUBTOTAL(9,F96:F98) | G95: =SUBTOTAL(9,G96:G98) | H95: =SUBTOTAL(9,H96:H98) | I95: =SUBTOTAL(9,I96:I98) | J95: =SUBTOTAL(9,J96:J98) | ... O95: =SUBTOTAL(9,O96:O98)
A96: 26.09 | B96: SIAE, SCF e diritti musicali | O96: =SUM(C96:N96)
A97: 26.10 | B97: Permessi, autorizzazioni e oneri evento | O97: =SUM(C97:N97)
A98: 26.11 | B98: Allestimenti e materiali evento | O98: =SUM(C98:N98)
A100: E | B100: COSTI DI STRUTTURA | C100: =SUBTOTAL(9,C101:C164) | D100: =SUBTOTAL(9,D101:D164) | E100: =SUBTOTAL(9,E101:E164) | F100: =SUBTOTAL(9,F101:F164) | G100: =SUBTOTAL(9,G101:G164) | H100: =SUBTOTAL(9,H101:H164) | I100: =SUBTOTAL(9,I101:I164) | J100: =SUBTOTAL(9,J101:J164) | ... O100: =SUBTOTAL(9,O101:O164)
A101: E1 | B101: Immobili e spazi | C101: =SUBTOTAL(9,C102:C104) | D101: =SUBTOTAL(9,D102:D104) | E101: =SUBTOTAL(9,E102:E104) | F101: =SUBTOTAL(9,F102:F104) | G101: =SUBTOTAL(9,G102:G104) | H101: =SUBTOTAL(9,H102:H104) | I101: =SUBTOTAL(9,I102:I104) | J101: =SUBTOTAL(9,J102:J104) | ... O101: =SUBTOTAL(9,O102:O104)
A102: 27.01 | B102: Affitti e locazioni immobili | O102: =SUM(C102:N102)
A103: 27.02 | B103: Spese condominiali | O103: =SUM(C103:N103)
A104: 27.03 | B104: Canoni concessori e demaniali | O104: =SUM(C104:N104)
A105: E2 | B105: Utenze | C105: =SUBTOTAL(9,C106:C111) | D105: =SUBTOTAL(9,D106:D111) | E105: =SUBTOTAL(9,E106:E111) | F105: =SUBTOTAL(9,F106:F111) | G105: =SUBTOTAL(9,G106:G111) | H105: =SUBTOTAL(9,H106:H111) | I105: =SUBTOTAL(9,I106:I111) | J105: =SUBTOTAL(9,J106:J111) | ... O105: =SUBTOTAL(9,O106:O111)
...

Sheet BUDGET
A1: BUDGET — obiettivo
A2: Stessa struttura del consuntivo, riga per riga. Compila le voci di dettaglio: sottogruppi, famiglie e margini si calcolano da soli.
A4: Codice | B4: Voce | C4: GEN | D4: FEB | E4: MAR | F4: APR | G4: MAG | H4: GIU | I4: LUG | J4: AGO | K4: SET | L4: OTT | M4: NOV | N4: DIC | O4: TOTALE
A5: A | B5: INCASSI OPERATIVI | C5: =SUBTOTAL(9,C6:C19) | D5: =SUBTOTAL(9,D6:D19) | E5: =SUBTOTAL(9,E6:E19) | F5: =SUBTOTAL(9,F6:F19) | G5: =SUBTOTAL(9,G6:G19) | H5: =SUBTOTAL(9,H6:H19) | I5: =SUBTOTAL(9,I6:I19) | J5: =SUBTOTAL(9,J6:J19) | ... O5: =SUBTOTAL(9,O6:O19)
A6: A1 | B6: Corrispettivi | C6: =SUBTOTAL(9,C7:C8) | D6: =SUBTOTAL(9,D7:D8) | E6: =SUBTOTAL(9,E7:E8) | F6: =SUBTOTAL(9,F7:F8) | G6: =SUBTOTAL(9,G7:G8) | H6: =SUBTOTAL(9,H7:H8) | I6: =SUBTOTAL(9,I7:I8) | J6: =SUBTOTAL(9,J7:J8) | ... O6: =SUBTOTAL(9,O7:O8)
A7: 10.01 | B7: Corrispettivi | O7: =SUM(C7:N7)
A8: 10.09 | B8: Resi, sconti e abbuoni su vendite | O8: =SUM(C8:N8)
A9: A2 | B9: Eventi | C9: =SUBTOTAL(9,C10:C11) | D9: =SUBTOTAL(9,D10:D11) | E9: =SUBTOTAL(9,E10:E11) | F9: =SUBTOTAL(9,F10:F11) | G9: =SUBTOTAL(9,G10:G11) | H9: =SUBTOTAL(9,H10:H11) | I9: =SUBTOTAL(9,I10:I11) | J9: =SUBTOTAL(9,J10:J11) | ... O9: =SUBTOTAL(9,O10:O11)
A10: 11.01 | B10: Ricavi eventi serali (ingressi e consumazioni) | O10: =SUM(C10:N10)
A11: 11.02 | B11: Ricavi eventi privati e compleanni | O11: =SUM(C11:N11)
A12: A3 | B12: Altri proventi | C12: =SUBTOTAL(9,C13:C19) | D12: =SUBTOTAL(9,D13:D19) | E12: =SUBTOTAL(9,E13:E19) | F12: =SUBTOTAL(9,F13:F19) | G12: =SUBTOTAL(9,G13:G19) | H12: =SUBTOTAL(9,H13:H19) | I12: =SUBTOTAL(9,I13:I19) | J12: =SUBTOTAL(9,J13:J19) | ... O12: =SUBTOTAL(9,O13:O19)
A13: 12.01 | B13: Proventi vari | O13: =SUM(C13:N13)
A14: 12.02 | B14: Contributi in conto esercizio | O14: =SUM(C14:N14)
A15: 12.03 | B15: Rimborsi assicurativi | O15: =SUM(C15:N15)
A16: 12.04 | B16: Premi, bonus e contributi da fornitori | O16: =SUM(C16:N16)
A17: 12.06 | B17: Sopravvenienze attive | O17: =SUM(C17:N17)
A18: 13.01 | B18: Interessi attivi bancari | O18: =SUM(C18:N18)
A19: 13.02 | B19: Altri proventi finanziari | O19: =SUM(C19:N19)
A21: B | B21: COSTO DEL VENDUTO | C21: =SUBTOTAL(9,C22:C51) | D21: =SUBTOTAL(9,D22:D51) | E21: =SUBTOTAL(9,E22:E51) | F21: =SUBTOTAL(9,F22:F51) | G21: =SUBTOTAL(9,G22:G51) | H21: =SUBTOTAL(9,H22:H51) | I21: =SUBTOTAL(9,I22:I51) | J21: =SUBTOTAL(9,J22:J51) | ... O21: =SUBTOTAL(9,O22:O51)
A22: B1 | B22: Beverage alcolico | C22: =SUBTOTAL(9,C23:C27) | D22: =SUBTOTAL(9,D23:D27) | E22: =SUBTOTAL(9,E23:E27) | F22: =SUBTOTAL(9,F23:F27) | G22: =SUBTOTAL(9,G23:G27) | H22: =SUBTOTAL(9,H23:H27) | I22: =SUBTOTAL(9,I23:I27) | J22: =SUBTOTAL(9,J23:J27) | ... O22: =SUBTOTAL(9,O23:O27)
A23: 20.1.01 | B23: Birra fusto | O23: =SUM(C23:N23)
A24: 20.1.02 | B24: Birra bottiglia e lattina | O24: =SUM(C24:N24)
A25: 20.1.03 | B25: Distillati e liquori | O25: =SUM(C25:N25)
A26: 20.1.04 | B26: Vermouth, bitter e aperitivi | O26: =SUM(C26:N26)
A27: 20.1.05 | B27: Vini | O27: =SUM(C27:N27)
A28: B2 | B28: Beverage analcolico | C28: =SUBTOTAL(9,C29:C32) | D28: =SUBTOTAL(9,D29:D32) | E28: =SUBTOTAL(9,E29:E32) | F28: =SUBTOTAL(9,F29:F32) | G28: =SUBTOTAL(9,G29:G32) | H28: =SUBTOTAL(9,H29:H32) | I28: =SUBTOTAL(9,I29:I32) | J28: =SUBTOTAL(9,J29:J32) | ... O28: =SUBTOTAL(9,O29:O32)
A29: 20.2.01 | B29: Bibite e soft drink | O29: =SUM(C29:N29)
A30: 20.2.02 | B30: Acqua minerale | O30: =SUM(C30:N30)
A31: 20.2.03 | B31: Succhi, nettari e centrifugati | O31: =SUM(C31:N31)
A32: 20.2.04 | B32: Sciroppi, purea e mixer | O32: =SUM(C32:N32)
A33: B3 | B33: Caffetteria | C33: =SUBTOTAL(9,C34:C37) | D33: =SUBTOTAL(9,D34:D37) | E33: =SUBTOTAL(9,E34:E37) | F33: =SUBTOTAL(9,F34:F37) | G33: =SUBTOTAL(9,G34:G37) | H33: =SUBTOTAL(9,H34:H37) | I33: =SUBTOTAL(9,I34:I37) | J33: =SUBTOTAL(9,J34:J37) | ... O33: =SUBTOTAL(9,O34:O37)
A34: 20.3.01 | B34: Caffè | O34: =SUM(C34:N34)
A35: 20.3.02 | B35: Latte e derivati | O35: =SUM(C35:N35)
A36: 20.3.03 | B36: Tè, infusi e cioccolata | O36: =SUM(C36:N36)
A37: 20.3.04 | B37: Zucchero e complementi caffetteria | O37: =SUM(C37:N37)
A38: B4 | B38: Food | C38: =SUBTOTAL(9,C39:C43) | D38: =SUBTOTAL(9,D39:D43) | E38: =SUBTOTAL(9,E39:E43) | F38: =SUBTOTAL(9,F39:F43) | G38: =SUBTOTAL(9,G39:G43) | H38: =SUBTOTAL(9,H39:H43) | I38: =SUBTOTAL(9,I39:I43) | J38: =SUBTOTAL(9,J39:J43) | ... O38: =SUBTOTAL(9,O39:O43)
A39: 20.4.01 | B39: Beni alimentari e gastronomia | O39: =SUM(C39:N39)
A40: 20.4.02 | B40: Frutta e verdura | O40: =SUM(C40:N40)
A41: 20.4.03 | B41: Pane e prodotti da forno | O41: =SUM(C41:N41)
A42: 20.4.04 | B42: Pasticceria e dolci | O42: =SUM(C42:N42)
A43: 20.4.05 | B43: Snack e prodotti confezionati | O43: =SUM(C43:N43)
A44: B5 | B44: Consumabili di servizio | C44: =SUBTOTAL(9,C45:C49) | D44: =SUBTOTAL(9,D45:D49) | E44: =SUBTOTAL(9,E45:E49) | F44: =SUBTOTAL(9,F45:F49) | G44: =SUBTOTAL(9,G45:G49) | H44: =SUBTOTAL(9,H45:H49) | I44: =SUBTOTAL(9,I45:I49) | J44: =SUBTOTAL(9,J45:J49) | ... O44: =SUBTOTAL(9,O45:O49)
A45: 20.5.01 | B45: Ghiaccio | O45: =SUM(C45:N45)
A46: 20.5.02 | B46: Garnish e decorazioni | O46: =SUM(C46:N46)
A47: 20.5.03 | B47: Monouso, packaging e asporto | O47: =SUM(C47:N47)
A48: 20.5.04 | B48: Materiale igiene e pulizia | O48: =SUM(C48:N48)
A49: 20.5.05 | B49: Altri materiali di consumo | O49: =SUM(C49:N49)
A50: B6 | B50: Rettifiche su acquisti | C50: =SUBTOTAL(9,C51:C51) | D50: =SUBTOTAL(9,D51:D51) | E50: =SUBTOTAL(9,E51:E51) | F50: =SUBTOTAL(9,F51:F51) | G50: =SUBTOTAL(9,G51:G51) | H50: =SUBTOTAL(9,H51:H51) | I50: =SUBTOTAL(9,I51:I51) | J50: =SUBTOTAL(9,J51:J51) | ... O50: =SUBTOTAL(9,O51:O51)
A51: 20.6.01 | B51: Resi, sconti e premi su acquisti | O51: =SUM(C51:N51)
B52: MARGINE DI CONTRIBUZIONE | C52: =C5+C21 | D52: =D5+D21 | E52: =E5+E21 | F52: =F5+F21 | G52: =G5+G21 | H52: =H5+H21 | I52: =I5+I21 | J52: =J5+J21 | ... O52: =O5+O21
A54: C | B54: COSTO DEL PERSONALE | C54: =SUBTOTAL(9,C55:C81) | D54: =SUBTOTAL(9,D55:D81) | E54: =SUBTOTAL(9,E55:E81) | F54: =SUBTOTAL(9,F55:F81) | G54: =SUBTOTAL(9,G55:G81) | H54: =SUBTOTAL(9,H55:H81) | I54: =SUBTOTAL(9,I55:I81) | J54: =SUBTOTAL(9,J55:J81) | ... O54: =SUBTOTAL(9,O55:O81)
A55: C1 | B55: Retribuzioni | C55: =SUBTOTAL(9,C56:C64) | D55: =SUBTOTAL(9,D56:D64) | E55: =SUBTOTAL(9,E56:E64) | F55: =SUBTOTAL(9,F56:F64) | G55: =SUBTOTAL(9,G56:G64) | H55: =SUBTOTAL(9,H56:H64) | I55: =SUBTOTAL(9,I56:I64) | J55: =SUBTOTAL(9,J56:J64) | ... O55: =SUBTOTAL(9,O56:O64)
A56: 28.1.01 | B56: Retribuzioni personale dipendente serale | O56: =SUM(C56:N56)
A57: 28.1.02 | B57: Retribuzioni personale extra e a chiamata | O57: =SUM(C57:N57)
A58: 28.1.03 | B58: Retribuzioni personale servizio mattina | O58: =SUM(C58:N58)
A59: 28.1.04 | B59: Retribuzioni personale extra mattina | O59: =SUM(C59:N59)
A60: 28.1.05 | B60: Retribuzioni personale pulizie | O60: =SUM(C60:N60)
A61: 28.1.06 | B61: Retribuzioni personale sicurezza | O61: =SUM(C61:N61)
A62: 28.1.07 | B62: Straordinari e maggiorazioni | O62: =SUM(C62:N62)
A63: 28.1.08 | B63: Ferie, permessi e mensilità aggiuntive | O63: =SUM(C63:N63)
A64: 28.1.09 | B64: Retribuzioni personale amministrativo | O64: =SUM(C64:N64)
A65: C2 | B65: Oneri sociali | C65: =SUBTOTAL(9,C66:C68) | D65: =SUBTOTAL(9,D66:D68) | E65: =SUBTOTAL(9,E66:E68) | F65: =SUBTOTAL(9,F66:F68) | G65: =SUBTOTAL(9,G66:G68) | H65: =SUBTOTAL(9,H66:H68) | I65: =SUBTOTAL(9,I66:I68) | J65: =SUBTOTAL(9,J66:J68) | ... O65: =SUBTOTAL(9,O66:O68)
A66: 28.2.01 | B66: Contributi INPS c/azienda | O66: =SUM(C66:N66)
A67: 28.2.02 | B67: Contributi INAIL | O67: =SUM(C67:N67)
A68: 28.2.03 | B68: Fondi integrativi ed enti bilaterali | O68: =SUM(C68:N68)
A69: C3 | B69: TFR corrisposto | C69: =SUBTOTAL(9,C70:C70) | D69: =SUBTOTAL(9,D70:D70) | E69: =SUBTOTAL(9,E70:E70) | F69: =SUBTOTAL(9,F70:F70) | G69: =SUBTOTAL(9,G70:G70) | H69: =SUBTOTAL(9,H70:H70) | I69: =SUBTOTAL(9,I70:I70) | J69: =SUBTOTAL(9,J70:J70) | ... O69: =SUBTOTAL(9,O70:O70)
A70: 28.3.02 | B70: TFR corrisposto nell'anno | O70: =SUM(C70:N70)
A71: C4 | B71: Altri costi del personale | C71: =SUBTOTAL(9,C72:C76) | D71: =SUBTOTAL(9,D72:D76) | E71: =SUBTOTAL(9,E72:E76) | F71: =SUBTOTAL(9,F72:F76) | G71: =SUBTOTAL(9,G72:G76) | H71: =SUBTOTAL(9,H72:H76) | I71: =SUBTOTAL(9,I72:I76) | J71: =SUBTOTAL(9,J72:J76) | ... O71: =SUBTOTAL(9,O72:O76)
A72: 28.4.01 | B72: Rimborsi spese dipendenti | O72: =SUM(C72:N72)
A73: 28.4.02 | B73: Welfare aziendale e fringe benefit | O73: =SUM(C73:N73)
A74: 28.4.03 | B74: Buoni pasto, vitto e alloggio | O74: =SUM(C74:N74)
A75: 28.4.04 | B75: Ricerca, selezione e tirocini | O75: =SUM(C75:N75)
A76: 28.4.05 | B76: Altri costi per personale dipendente | O76: =SUM(C76:N76)
A77: C5 | B77: Organi sociali e collaborazioni | C77: =SUBTOTAL(9,C78:C81) | D77: =SUBTOTAL(9,D78:D81) | E77: =SUBTOTAL(9,E78:E81) | F77: =SUBTOTAL(9,F78:F81) | G77: =SUBTOTAL(9,G78:G81) | H77: =SUBTOTAL(9,H78:H81) | I77: =SUBTOTAL(9,I78:I81) | J77: =SUBTOTAL(9,J78:J81) | ... O77: =SUBTOTAL(9,O78:O81)
A78: 29.01 | B78: Compenso amministratore | O78: =SUM(C78:N78)
A79: 29.02 | B79: Contributi INPS gestione separata amministratore | O79: =SUM(C79:N79)
A80: 29.04 | B80: Rimborsi spese amministratore | O80: =SUM(C80:N80)
A81: 29.05 | B81: Compensi per collaborazioni e prestazioni occasionali | O81: =SUM(C81:N81)
A83: D | B83: COSTI DIRETTI EVENTI | C83: =SUBTOTAL(9,C84:C98) | D83: =SUBTOTAL(9,D84:D98) | E83: =SUBTOTAL(9,E84:E98) | F83: =SUBTOTAL(9,F84:F98) | G83: =SUBTOTAL(9,G84:G98) | H83: =SUBTOTAL(9,H84:H98) | I83: =SUBTOTAL(9,I84:I98) | J83: =SUBTOTAL(9,J84:J98) | ... O83: =SUBTOTAL(9,O84:O98)
A84: D1 | B84: Artisti e service | C84: =SUBTOTAL(9,C85:C86) | D84: =SUBTOTAL(9,D85:D86) | E84: =SUBTOTAL(9,E85:E86) | F84: =SUBTOTAL(9,F85:F86) | G84: =SUBTOTAL(9,G85:G86) | H84: =SUBTOTAL(9,H85:H86) | I84: =SUBTOTAL(9,I85:I86) | J84: =SUBTOTAL(9,J85:J86) | ... O84: =SUBTOTAL(9,O85:O86)
A85: 26.01 | B85: Artisti, DJ e compensi live | O85: =SUM(C85:N85)
A86: 26.02 | B86: Service audio-luci e noleggi tecnici | O86: =SUM(C86:N86)
A87: D2 | B87: Manodopera evento | C87: =SUBTOTAL(9,C88:C90) | D87: =SUBTOTAL(9,D88:D90) | E87: =SUBTOTAL(9,E88:E90) | F87: =SUBTOTAL(9,F88:F90) | G87: =SUBTOTAL(9,G88:G90) | H87: =SUBTOTAL(9,H88:H90) | I87: =SUBTOTAL(9,I88:I90) | J87: =SUBTOTAL(9,J88:J90) | ... O87: =SUBTOTAL(9,O88:O90)
A88: 26.03 | B88: Personale evento | O88: =SUM(C88:N88)
A89: 26.05 | B89: Sicurezza e steward evento | O89: =SUM(C89:N89)
A90: 26.06 | B90: Servizi di pulizia evento | O90: =SUM(C90:N90)
A91: D3 | B91: Promozione evento | C91: =SUBTOTAL(9,C92:C94) | D91: =SUBTOTAL(9,D92:D94) | E91: =SUBTOTAL(9,E92:E94) | F91: =SUBTOTAL(9,F92:F94) | G91: =SUBTOTAL(9,G92:G94) | H91: =SUBTOTAL(9,H92:H94) | I91: =SUBTOTAL(9,I92:I94) | J91: =SUBTOTAL(9,J92:J94) | ... O91: =SUBTOTAL(9,O92:O94)
A92: 26.04 | B92: PR e promoter evento | O92: =SUM(C92:N92)
A93: 26.07 | B93: Advertising e sponsorizzate evento | O93: =SUM(C93:N93)
A94: 26.08 | B94: Foto e grafiche evento | O94: =SUM(C94:N94)
A95: D4 | B95: Oneri e allestimenti evento | C95: =SUBTOTAL(9,C96:C98) | D95: =SUBTOTAL(9,D96:D98) | E95: =SUBTOTAL(9,E96:E98) | F95: =SUBTOTAL(9,F96:F98) | G95: =SUBTOTAL(9,G96:G98) | H95: =SUBTOTAL(9,H96:H98) | I95: =SUBTOTAL(9,I96:I98) | J95: =SUBTOTAL(9,J96:J98) | ... O95: =SUBTOTAL(9,O96:O98)
A96: 26.09 | B96: SIAE, SCF e diritti musicali | O96: =SUM(C96:N96)
A97: 26.10 | B97: Permessi, autorizzazioni e oneri evento | O97: =SUM(C97:N97)
A98: 26.11 | B98: Allestimenti e materiali evento | O98: =SUM(C98:N98)
A100: E | B100: COSTI DI STRUTTURA | C100: =SUBTOTAL(9,C101:C164) | D100: =SUBTOTAL(9,D101:D164) | E100: =SUBTOTAL(9,E101:E164) | F100: =SUBTOTAL(9,F101:F164) | G100: =SUBTOTAL(9,G101:G164) | H100: =SUBTOTAL(9,H101:H164) | I100: =SUBTOTAL(9,I101:I164) | J100: =SUBTOTAL(9,J101:J164) | ... O100: =SUBTOTAL(9,O101:O164)
A101: E1 | B101: Immobili e spazi | C101: =SUBTOTAL(9,C102:C104) | D101: =SUBTOTAL(9,D102:D104) | E101: =SUBTOTAL(9,E102:E104) | F101: =SUBTOTAL(9,F102:F104) | G101: =SUBTOTAL(9,G102:G104) | H101: =SUBTOTAL(9,H102:H104) | I101: =SUBTOTAL(9,I102:I104) | J101: =SUBTOTAL(9,J102:J104) | ... O101: =SUBTOTAL(9,O102:O104)
A102: 27.01 | B102: Affitti e locazioni immobili | O102: =SUM(C102:N102)
A103: 27.02 | B103: Spese condominiali | O103: =SUM(C103:N103)
A104: 27.03 | B104: Canoni concessori e demaniali | O104: =SUM(C104:N104)
A105: E2 | B105: Utenze | C105: =SUBTOTAL(9,C106:C111) | D105: =SUBTOTAL(9,D106:D111) | E105: =SUBTOTAL(9,E106:E111) | F105: =SUBTOTAL(9,F106:F111) | G105: =SUBTOTAL(9,G106:G111) | H105: =SUBTOTAL(9,H106:H111) | I105: =SUBTOTAL(9,I106:I111) | J105: =SUBTOTAL(9,J106:J111) | ... O105: =SUBTOTAL(9,O106:O111)
...

Sheet SCOSTAMENTO
A1: SCOSTAMENTO — consuntivo contro budget
A2: Differenza in euro e in percentuale. Le righe rispecchiano una per una quelle di CASH FLOW e BUDGET: stessa altezza, stessi codici.
A4: Codice | B4: Voce | C4: GEN | D4: FEB | E4: MAR | F4: APR | G4: MAG | H4: GIU | I4: LUG | J4: AGO | K4: SET | L4: OTT | M4: NOV | N4: DIC | O4: TOTALE | Q4: Scost. %
A5: ='CASH FLOW'!A5 | B5: ='CASH FLOW'!B5 | C5: =IF(AND('CASH FLOW'!C5=0,BUDGET!C5=0),"",'CASH FLOW'!C5-BUDGET!C5) | D5: =IF(AND('CASH FLOW'!D5=0,BUDGET!D5=0),"",'CASH FLOW'!D5-BUDGET!D5) | E5: =IF(AND('CASH FLOW'!E5=0,BUDGET!E5=0),"",'CASH FLOW'!E5-BUDGET!E5) | F5: =IF(AND('CASH FLOW'!F5=0,BUDGET!F5=0),"",'CASH FLOW'!F5-BUDGET!F5) | G5: =IF(AND('CASH FLOW'!G5=0,BUDGET!G5=0),"",'CASH FLOW'!G5-BUDGET!G5) | H5: =IF(AND('CASH FLOW'!H5=0,BUDGET!H5=0),"",'CASH FLOW'!H5-BUDGET!H5) | I5: =IF(AND('CASH FLOW'!I5=0,BUDGET!I5=0),"",'CASH FLOW'!I5-BUDGET!I5) | J5: =IF(AND('CASH FLOW'!J5=0,BUDGET!J5=0),"",'CASH FLOW'!J5-BUDGET!J5) | ... O5: =IF(AND('CASH FLOW'!O5=0,BUDGET!O5=0),"",'CASH FLOW'!O5-BUDGET!O5) | Q5: =IF(BUDGET!O5=0,"",('CASH FLOW'!O5-BUDGET!O5)/ABS(BUDGET!O5))
A6: ='CASH FLOW'!A6 | B6: ='CASH FLOW'!B6 | C6: =IF(AND('CASH FLOW'!C6=0,BUDGET!C6=0),"",'CASH FLOW'!C6-BUDGET!C6) | D6: =IF(AND('CASH FLOW'!D6=0,BUDGET!D6=0),"",'CASH FLOW'!D6-BUDGET!D6) | E6: =IF(AND('CASH FLOW'!E6=0,BUDGET!E6=0),"",'CASH FLOW'!E6-BUDGET!E6) | F6: =IF(AND('CASH FLOW'!F6=0,BUDGET!F6=0),"",'CASH FLOW'!F6-BUDGET!F6) | G6: =IF(AND('CASH FLOW'!G6=0,BUDGET!G6=0),"",'CASH FLOW'!G6-BUDGET!G6) | H6: =IF(AND('CASH FLOW'!H6=0,BUDGET!H6=0),"",'CASH FLOW'!H6-BUDGET!H6) | I6: =IF(AND('CASH FLOW'!I6=0,BUDGET!I6=0),"",'CASH FLOW'!I6-BUDGET!I6) | J6: =IF(AND('CASH FLOW'!J6=0,BUDGET!J6=0),"",'CASH FLOW'!J6-BUDGET!J6) | ... O6: =IF(AND('CASH FLOW'!O6=0,BUDGET!O6=0),"",'CASH FLOW'!O6-BUDGET!O6) | Q6: =IF(BUDGET!O6=0,"",('CASH FLOW'!O6-BUDGET!O6)/ABS(BUDGET!O6))
A7: ='CASH FLOW'!A7 | B7: ='CASH FLOW'!B7 | C7: =IF(AND('CASH FLOW'!C7=0,BUDGET!C7=0),"",'CASH FLOW'!C7-BUDGET!C7) | D7: =IF(AND('CASH FLOW'!D7=0,BUDGET!D7=0),"",'CASH FLOW'!D7-BUDGET!D7) | E7: =IF(AND('CASH FLOW'!E7=0,BUDGET!E7=0),"",'CASH FLOW'!E7-BUDGET!E7) | F7: =IF(AND('CASH FLOW'!F7=0,BUDGET!F7=0),"",'CASH FLOW'!F7-BUDGET!F7) | G7: =IF(AND('CASH FLOW'!G7=0,BUDGET!G7=0),"",'CASH FLOW'!G7-BUDGET!G7) | H7: =IF(AND('CASH FLOW'!H7=0,BUDGET!H7=0),"",'CASH FLOW'!H7-BUDGET!H7) | I7: =IF(AND('CASH FLOW'!I7=0,BUDGET!I7=0),"",'CASH FLOW'!I7-BUDGET!I7) | J7: =IF(AND('CASH FLOW'!J7=0,BUDGET!J7=0),"",'CASH FLOW'!J7-BUDGET!J7) | ... O7: =IF(AND('CASH FLOW'!O7=0,BUDGET!O7=0),"",'CASH FLOW'!O7-BUDGET!O7) | Q7: =IF(BUDGET!O7=0,"",('CASH FLOW'!O7-BUDGET!O7)/ABS(BUDGET!O7))
A8: ='CASH FLOW'!A8 | B8: ='CASH FLOW'!B8 | C8: =IF(AND('CASH FLOW'!C8=0,BUDGET!C8=0),"",'CASH FLOW'!C8-BUDGET!C8) | D8: =IF(AND('CASH FLOW'!D8=0,BUDGET!D8=0),"",'CASH FLOW'!D8-BUDGET!D8) | E8: =IF(AND('CASH FLOW'!E8=0,BUDGET!E8=0),"",'CASH FLOW'!E8-BUDGET!E8) | F8: =IF(AND('CASH FLOW'!F8=0,BUDGET!F8=0),"",'CASH FLOW'!F8-BUDGET!F8) | G8: =IF(AND('CASH FLOW'!G8=0,BUDGET!G8=0),"",'CASH FLOW'!G8-BUDGET!G8) | H8: =IF(AND('CASH FLOW'!H8=0,BUDGET!H8=0),"",'CASH FLOW'!H8-BUDGET!H8) | I8: =IF(AND('CASH FLOW'!I8=0,BUDGET!I8=0),"",'CASH FLOW'!I8-BUDGET!I8) | J8: =IF(AND('CASH FLOW'!J8=0,BUDGET!J8=0),"",'CASH FLOW'!J8-BUDGET!J8) | ... O8: =IF(AND('CASH FLOW'!O8=0,BUDGET!O8=0),"",'CASH FLOW'!O8-BUDGET!O8) | Q8: =IF(BUDGET!O8=0,"",('CASH FLOW'!O8-BUDGET!O8)/ABS(BUDGET!O8))
A9: ='CASH FLOW'!A9 | B9: ='CASH FLOW'!B9 | C9: =IF(AND('CASH FLOW'!C9=0,BUDGET!C9=0),"",'CASH FLOW'!C9-BUDGET!C9) | D9: =IF(AND('CASH FLOW'!D9=0,BUDGET!D9=0),"",'CASH FLOW'!D9-BUDGET!D9) | E9: =IF(AND('CASH FLOW'!E9=0,BUDGET!E9=0),"",'CASH FLOW'!E9-BUDGET!E9) | F9: =IF(AND('CASH FLOW'!F9=0,BUDGET!F9=0),"",'CASH FLOW'!F9-BUDGET!F9) | G9: =IF(AND('CASH FLOW'!G9=0,BUDGET!G9=0),"",'CASH FLOW'!G9-BUDGET!G9) | H9: =IF(AND('CASH FLOW'!H9=0,BUDGET!H9=0),"",'CASH FLOW'!H9-BUDGET!H9) | I9: =IF(AND('CASH FLOW'!I9=0,BUDGET!I9=0),"",'CASH FLOW'!I9-BUDGET!I9) | J9: =IF(AND('CASH FLOW'!J9=0,BUDGET!J9=0),"",'CASH FLOW'!J9-BUDGET!J9) | ... O9: =IF(AND('CASH FLOW'!O9=0,BUDGET!O9=0),"",'CASH FLOW'!O9-BUDGET!O9) | Q9: =IF(BUDGET!O9=0,"",('CASH FLOW'!O9-BUDGET!O9)/ABS(BUDGET!O9))
A10: ='CASH FLOW'!A10 | B10: ='CASH FLOW'!B10 | C10: =IF(AND('CASH FLOW'!C10=0,BUDGET!C10=0),"",'CASH FLOW'!C10-BUDGET!C10) | D10: =IF(AND('CASH FLOW'!D10=0,BUDGET!D10=0),"",'CASH FLOW'!D10-BUDGET!D10) | E10: =IF(AND('CASH FLOW'!E10=0,BUDGET!E10=0),"",'CASH FLOW'!E10-BUDGET!E10) | F10: =IF(AND('CASH FLOW'!F10=0,BUDGET!F10=0),"",'CASH FLOW'!F10-BUDGET!F10) | G10: =IF(AND('CASH FLOW'!G10=0,BUDGET!G10=0),"",'CASH FLOW'!G10-BUDGET!G10) | H10: =IF(AND('CASH FLOW'!H10=0,BUDGET!H10=0),"",'CASH FLOW'!H10-BUDGET!H10) | I10: =IF(AND('CASH FLOW'!I10=0,BUDGET!I10=0),"",'CASH FLOW'!I10-BUDGET!I10) | J10: =IF(AND('CASH FLOW'!J10=0,BUDGET!J10=0),"",'CASH FLOW'!J10-BUDGET!J10) | ... O10: =IF(AND('CASH FLOW'!O10=0,BUDGET!O10=0),"",'CASH FLOW'!O10-BUDGET!O10) | Q10: =IF(BUDGET!O10=0,"",('CASH FLOW'!O10-BUDGET!O10)/ABS(BUDGET!O10))
A11: ='CASH FLOW'!A11 | B11: ='CASH FLOW'!B11 | C11: =IF(AND('CASH FLOW'!C11=0,BUDGET!C11=0),"",'CASH FLOW'!C11-BUDGET!C11) | D11: =IF(AND('CASH FLOW'!D11=0,BUDGET!D11=0),"",'CASH FLOW'!D11-BUDGET!D11) | E11: =IF(AND('CASH FLOW'!E11=0,BUDGET!E11=0),"",'CASH FLOW'!E11-BUDGET!E11) | F11: =IF(AND('CASH FLOW'!F11=0,BUDGET!F11=0),"",'CASH FLOW'!F11-BUDGET!F11) | G11: =IF(AND('CASH FLOW'!G11=0,BUDGET!G11=0),"",'CASH FLOW'!G11-BUDGET!G11) | H11: =IF(AND('CASH FLOW'!H11=0,BUDGET!H11=0),"",'CASH FLOW'!H11-BUDGET!H11) | I11: =IF(AND('CASH FLOW'!I11=0,BUDGET!I11=0),"",'CASH FLOW'!I11-BUDGET!I11) | J11: =IF(AND('CASH FLOW'!J11=0,BUDGET!J11=0),"",'CASH FLOW'!J11-BUDGET!J11) | ... O11: =IF(AND('CASH FLOW'!O11=0,BUDGET!O11=0),"",'CASH FLOW'!O11-BUDGET!O11) | Q11: =IF(BUDGET!O11=0,"",('CASH FLOW'!O11-BUDGET!O11)/ABS(BUDGET!O11))
A12: ='CASH FLOW'!A12 | B12: ='CASH FLOW'!B12 | C12: =IF(AND('CASH FLOW'!C12=0,BUDGET!C12=0),"",'CASH FLOW'!C12-BUDGET!C12) | D12: =IF(AND('CASH FLOW'!D12=0,BUDGET!D12=0),"",'CASH FLOW'!D12-BUDGET!D12) | E12: =IF(AND('CASH FLOW'!E12=0,BUDGET!E12=0),"",'CASH FLOW'!E12-BUDGET!E12) | F12: =IF(AND('CASH FLOW'!F12=0,BUDGET!F12=0),"",'CASH FLOW'!F12-BUDGET!F12) | G12: =IF(AND('CASH FLOW'!G12=0,BUDGET!G12=0),"",'CASH FLOW'!G12-BUDGET!G12) | H12: =IF(AND('CASH FLOW'!H12=0,BUDGET!H12=0),"",'CASH FLOW'!H12-BUDGET!H12) | I12: =IF(AND('CASH FLOW'!I12=0,BUDGET!I12=0),"",'CASH FLOW'!I12-BUDGET!I12) | J12: =IF(AND('CASH FLOW'!J12=0,BUDGET!J12=0),"",'CASH FLOW'!J12-BUDGET!J12) | ... O12: =IF(AND('CASH FLOW'!O12=0,BUDGET!O12=0),"",'CASH FLOW'!O12-BUDGET!O12) | Q12: =IF(BUDGET!O12=0,"",('CASH FLOW'!O12-BUDGET!O12)/ABS(BUDGET!O12))
A13: ='CASH FLOW'!A13 | B13: ='CASH FLOW'!B13 | C13: =IF(AND('CASH FLOW'!C13=0,BUDGET!C13=0),"",'CASH FLOW'!C13-BUDGET!C13) | D13: =IF(AND('CASH FLOW'!D13=0,BUDGET!D13=0),"",'CASH FLOW'!D13-BUDGET!D13) | E13: =IF(AND('CASH FLOW'!E13=0,BUDGET!E13=0),"",'CASH FLOW'!E13-BUDGET!E13) | F13: =IF(AND('CASH FLOW'!F13=0,BUDGET!F13=0),"",'CASH FLOW'!F13-BUDGET!F13) | G13: =IF(AND('CASH FLOW'!G13=0,BUDGET!G13=0),"",'CASH FLOW'!G13-BUDGET!G13) | H13: =IF(AND('CASH FLOW'!H13=0,BUDGET!H13=0),"",'CASH FLOW'!H13-BUDGET!H13) | I13: =IF(AND('CASH FLOW'!I13=0,BUDGET!I13=0),"",'CASH FLOW'!I13-BUDGET!I13) | J13: =IF(AND('CASH FLOW'!J13=0,BUDGET!J13=0),"",'CASH FLOW'!J13-BUDGET!J13) | ... O13: =IF(AND('CASH FLOW'!O13=0,BUDGET!O13=0),"",'CASH FLOW'!O13-BUDGET!O13) | Q13: =IF(BUDGET!O13=0,"",('CASH FLOW'!O13-BUDGET!O13)/ABS(BUDGET!O13))
A14: ='CASH FLOW'!A14 | B14: ='CASH FLOW'!B14 | C14: =IF(AND('CASH FLOW'!C14=0,BUDGET!C14=0),"",'CASH FLOW'!C14-BUDGET!C14) | D14: =IF(AND('CASH FLOW'!D14=0,BUDGET!D14=0),"",'CASH FLOW'!D14-BUDGET!D14) | E14: =IF(AND('CASH FLOW'!E14=0,BUDGET!E14=0),"",'CASH FLOW'!E14-BUDGET!E14) | F14: =IF(AND('CASH FLOW'!F14=0,BUDGET!F14=0),"",'CASH FLOW'!F14-BUDGET!F14) | G14: =IF(AND('CASH FLOW'!G14=0,BUDGET!G14=0),"",'CASH FLOW'!G14-BUDGET!G14) | H14: =IF(AND('CASH FLOW'!H14=0,BUDGET!H14=0),"",'CASH FLOW'!H14-BUDGET!H14) | I14: =IF(AND('CASH FLOW'!I14=0,BUDGET!I14=0),"",'CASH FLOW'!I14-BUDGET!I14) | J14: =IF(AND('CASH FLOW'!J14=0,BUDGET!J14=0),"",'CASH FLOW'!J14-BUDGET!J14) | ... O14: =IF(AND('CASH FLOW'!O14=0,BUDGET!O14=0),"",'CASH FLOW'!O14-BUDGET!O14) | Q14: =IF(BUDGET!O14=0,"",('CASH FLOW'!O14-BUDGET!O14)/ABS(BUDGET!O14))
A15: ='CASH FLOW'!A15 | B15: ='CASH FLOW'!B15 | C15: =IF(AND('CASH FLOW'!C15=0,BUDGET!C15=0),"",'CASH FLOW'!C15-BUDGET!C15) | D15: =IF(AND('CASH FLOW'!D15=0,BUDGET!D15=0),"",'CASH FLOW'!D15-BUDGET!D15) | E15: =IF(AND('CASH FLOW'!E15=0,BUDGET!E15=0),"",'CASH FLOW'!E15-BUDGET!E15) | F15: =IF(AND('CASH FLOW'!F15=0,BUDGET!F15=0),"",'CASH FLOW'!F15-BUDGET!F15) | G15: =IF(AND('CASH FLOW'!G15=0,BUDGET!G15=0),"",'CASH FLOW'!G15-BUDGET!G15) | H15: =IF(AND('CASH FLOW'!H15=0,BUDGET!H15=0),"",'CASH FLOW'!H15-BUDGET!H15) | I15: =IF(AND('CASH FLOW'!I15=0,BUDGET!I15=0),"",'CASH FLOW'!I15-BUDGET!I15) | J15: =IF(AND('CASH FLOW'!J15=0,BUDGET!J15=0),"",'CASH FLOW'!J15-BUDGET!J15) | ... O15: =IF(AND('CASH FLOW'!O15=0,BUDGET!O15=0),"",'CASH FLOW'!O15-BUDGET!O15) | Q15: =IF(BUDGET!O15=0,"",('CASH FLOW'!O15-BUDGET!O15)/ABS(BUDGET!O15))
A16: ='CASH FLOW'!A16 | B16: ='CASH FLOW'!B16 | C16: =IF(AND('CASH FLOW'!C16=0,BUDGET!C16=0),"",'CASH FLOW'!C16-BUDGET!C16) | D16: =IF(AND('CASH FLOW'!D16=0,BUDGET!D16=0),"",'CASH FLOW'!D16-BUDGET!D16) | E16: =IF(AND('CASH FLOW'!E16=0,BUDGET!E16=0),"",'CASH FLOW'!E16-BUDGET!E16) | F16: =IF(AND('CASH FLOW'!F16=0,BUDGET!F16=0),"",'CASH FLOW'!F16-BUDGET!F16) | G16: =IF(AND('CASH FLOW'!G16=0,BUDGET!G16=0),"",'CASH FLOW'!G16-BUDGET!G16) | H16: =IF(AND('CASH FLOW'!H16=0,BUDGET!H16=0),"",'CASH FLOW'!H16-BUDGET!H16) | I16: =IF(AND('CASH FLOW'!I16=0,BUDGET!I16=0),"",'CASH FLOW'!I16-BUDGET!I16) | J16: =IF(AND('CASH FLOW'!J16=0,BUDGET!J16=0),"",'CASH FLOW'!J16-BUDGET!J16) | ... O16: =IF(AND('CASH FLOW'!O16=0,BUDGET!O16=0),"",'CASH FLOW'!O16-BUDGET!O16) | Q16: =IF(BUDGET!O16=0,"",('CASH FLOW'!O16-BUDGET!O16)/ABS(BUDGET!O16))
... A222: ='CASH FLOW'!A222 | B222: ='CASH FLOW'!B222 | C222: =IF(AND('CASH FLOW'!C222=0,BUDGET!C222=0),"",'CASH FLOW'!C222-BUDGET!C222) | D222: =IF(AND('CASH FLOW'!D222=0,BUDGET!D222=0),"",'CASH FLOW'!D222-BUDGET!D222) | E222: =IF(AND('CASH FLOW'!E222=0,BUDGET!E222=0),"",'CASH FLOW'!E222-BUDGET!E222) | F222: =IF(AND('CASH FLOW'!F222=0,BUDGET!F222=0),"",'CASH FLOW'!F222-BUDGET!F222) | G222: =IF(AND('CASH FLOW'!G222=0,BUDGET!G222=0),"",'CASH FLOW'!G222-BUDGET!G222) | H222: =IF(AND('CASH FLOW'!H222=0,BUDGET!H222=0),"",'CASH FLOW'!H222-BUDGET!H222) | I222: =IF(AND('CASH FLOW'!I222=0,BUDGET!I222=0),"",'CASH FLOW'!I222-BUDGET!I222) | J222: =IF(AND('CASH FLOW'!J222=0,BUDGET!J222=0),"",'CASH FLOW'!J222-BUDGET!J222) | ... O222: =IF(AND('CASH FLOW'!O222=0,BUDGET!O222=0),"",'CASH FLOW'!O222-BUDGET!O222) | Q222: =IF(BUDGET!O222=0,"",('CASH FLOW'!O222-BUDGET!O222)/ABS(BUDGET!O222))

Sheet PER CENTRO
A1: LETTURA PER CENTRO DI COSTO — totali dell'anno
A2: Il centro segue l'attivita', non il conto corrente. I costi comuni restano su STR: il ribaltamento in fondo e' un calcolo di analisi, non scrive movimenti.
A4: Codice | B4: Voce | C4: STR | D4: WEISS | E4: VV | F4: CAS | G4: TOTALE | I4: Quadratura
A5: A | B5: INCASSI OPERATIVI | C5: =SUM(C6:C8) | D5: =SUM(D6:D8) | E5: =SUM(E6:E8) | F5: =SUM(F6:F8) | G5: =SUM(G6:G8) | I5: =IF(ROUND(G5-'CASH FLOW'!O5,2)=0,"ok","non torna")
A6: A1 | B6: Corrispettivi | G6: =SUM(C6:F6)
A7: A2 | B7: Eventi | G7: =SUM(C7:F7)
A8: A3 | B8: Altri proventi | G8: =SUM(C8:F8)
A10: B | B10: COSTO DEL VENDUTO | C10: =SUM(C11:C16) | D10: =SUM(D11:D16) | E10: =SUM(E11:E16) | F10: =SUM(F11:F16) | G10: =SUM(G11:G16) | I10: =IF(ROUND(G10-'CASH FLOW'!O21,2)=0,"ok","non torna")
A11: B1 | B11: Beverage alcolico | G11: =SUM(C11:F11)
A12: B2 | B12: Beverage analcolico | G12: =SUM(C12:F12)
A13: B3 | B13: Caffetteria | G13: =SUM(C13:F13)
A14: B4 | B14: Food | G14: =SUM(C14:F14)
A15: B5 | B15: Consumabili di servizio | G15: =SUM(C15:F15)
A16: B6 | B16: Rettifiche su acquisti | G16: =SUM(C16:F16)
A18: C | B18: COSTO DEL PERSONALE | C18: =SUM(C19:C23) | D18: =SUM(D19:D23) | E18: =SUM(E19:E23) | F18: =SUM(F19:F23) | G18: =SUM(G19:G23) | I18: =IF(ROUND(G18-'CASH FLOW'!O54,2)=0,"ok","non torna")
A19: C1 | B19: Retribuzioni | G19: =SUM(C19:F19)
A20: C2 | B20: Oneri sociali | G20: =SUM(C20:F20)
A21: C3 | B21: TFR corrisposto | G21: =SUM(C21:F21)
A22: C4 | B22: Altri costi del personale | G22: =SUM(C22:F22)
A23: C5 | B23: Organi sociali e collaborazioni | G23: =SUM(C23:F23)
A25: D | B25: COSTI DIRETTI EVENTI | C25: =SUM(C26:C29) | D25: =SUM(D26:D29) | E25: =SUM(E26:E29) | F25: =SUM(F26:F29) | G25: =SUM(G26:G29) | I25: =IF(ROUND(G25-'CASH FLOW'!O83,2)=0,"ok","non torna")
A26: D1 | B26: Artisti e service | G26: =SUM(C26:F26)
A27: D2 | B27: Manodopera evento | G27: =SUM(C27:F27)
A28: D3 | B28: Promozione evento | G28: =SUM(C28:F28)
A29: D4 | B29: Oneri e allestimenti evento | G29: =SUM(C29:F29)
A31: E | B31: COSTI DI STRUTTURA | C31: =SUM(C32:C39) | D31: =SUM(D32:D39) | E31: =SUM(E32:E39) | F31: =SUM(F32:F39) | G31: =SUM(G32:G39) | I31: =IF(ROUND(G31-'CASH FLOW'!O100,2)=0,"ok","non torna")
A32: E1 | B32: Immobili e spazi | G32: =SUM(C32:F32)
A33: E2 | B33: Utenze | G33: =SUM(C33:F33)
A34: E3 | B34: Noleggi, leasing e licenze | G34: =SUM(C34:F34)
A35: E4 | B35: Manutenzioni e servizi operativi | G35: =SUM(C35:F35)
A36: E5 | B36: Attrezzatura e allestimenti | G36: =SUM(C36:F36)
A37: E6 | B37: Servizi professionali e amministrativi | G37: =SUM(C37:F37)
A38: E7 | B38: Marketing e comunicazione | G38: =SUM(C38:F38)
A39: E8 | B39: Tributi, assicurazioni e oneri diversi | G39: =SUM(C39:F39)
A41: F | B41: ONERI FINANZIARI | C41: =SUM(C42:C44) | D41: =SUM(D42:D44) | E41: =SUM(E42:E44) | F41: =SUM(F42:F44) | G41: =SUM(G42:G44) | I41: =IF(ROUND(G41-'CASH FLOW'!O166,2)=0,"ok","non torna")
A42: F1 | B42: Interessi passivi | G42: =SUM(C42:F42)
A43: F2 | B43: Spese e servizi bancari | G43: =SUM(C43:F43)
A44: F3 | B44: Commissioni su incassi | G44: =SUM(C44:F44)
A46: G | B46: FISCO E IVA | C46: =SUM(C47:C51) | D46: =SUM(D47:D51) | E46: =SUM(E47:E51) | F46: =SUM(F47:F51) | G46: =SUM(G47:G51) | I46: =IF(ROUND(G46-'CASH FLOW'!O185,2)=0,"ok","non torna")
A47: G1 | B47: IVA incassata sui corrispettivi | G47: =SUM(C47:F47)
A48: G2 | B48: IVA pagata sugli acquisti | G48: =SUM(C48:F48)
A49: G3 | B49: F24 IVA | G49: =SUM(C49:F49)
A50: G4 | B50: Imposte sul reddito | G50: =SUM(C50:F50)
A51: G5 | B51: Ritenute e contributi | G51: =SUM(C51:F51)
A53: H | B53: INVESTIMENTI | C53: =SUM(C54:C55) | D53: =SUM(D54:D55) | E53: =SUM(E54:E55) | F53: =SUM(F54:F55) | G53: =SUM(G54:G55) | I53: =IF(ROUND(G53-'CASH FLOW'!O196,2)=0,"ok","non torna")
A54: H1 | B54: Acquisto immobilizzazioni | G54: =SUM(C54:F54)
A55: H2 | B55: Cessione cespiti | G55: =SUM(C55:F55)
A57: I | B57: FINANZIAMENTI | C57: =SUM(C58:C60) | D57: =SUM(D58:D60) | E57: =SUM(E58:E60) | F57: =SUM(F58:F60) | G57: =SUM(G58:G60) | I57: =IF(ROUND(G57-'CASH FLOW'!O204,2)=0,"ok","non torna")
A58: I1 | B58: Rimborso capitale | G58: =SUM(C58:F58)
A59: I2 | B59: Nuova finanza | G59: =SUM(C59:F59)
A60: I3 | B60: Soci | G60: =SUM(C60:F60)
B64: RIBALTAMENTO DEI COSTI COMUNI (STR)
B65: Chiavi percentuali modificabili. Ogni riga deve sommare al 100%.
A66: Chiave | B66: Base di riparto | C66: WEISS % | D66: VV % | E66: CAS % | F66: Totale
A67: Generale | B67: quota decisa a tavolino, default | C67: 0.6 | D67: 0.3 | E67: 0.1 | F67: =SUM(C67:E67)
A68: Per ricavi | B68: peso dei corrispettivi di ciascun centro | F68: =SUM(C68:E68)
A69: Per personale | B69: peso del costo del personale operativo | F69: =SUM(C69:E69)
A70: Per superficie | B70: metri quadri occupati, utile sugli immobili | F70: =SUM(C70:E70)

Sheet SINTESI
A1: SINTESI — indicatori dell'anno
A2: Tutti gli indicatori leggono la colonna TOTALE del foglio CASH FLOW.
B4: VOLUMI
B5: Incassi operativi | C5: ='CASH FLOW'!O5 | D5: Corrispettivi, eventi e altri proventi, al netto IVA
B6: Giorni di apertura | D6: Da compilare: serve alla media giornaliera
B7: Incasso medio giornaliero | C7: =IF(C6=0,"",C5/C6) | D7: Incassi operativi diviso giorni di apertura
B9: MARGINI
B10: Margine di contribuzione | C10: ='CASH FLOW'!O52 | D10: Incassi meno costo del venduto
B11: Margine di contribuzione % | C11: =IF('CASH FLOW'!O5=0,"",'CASH FLOW'!O52/'CASH FLOW'!O5)
B12: Incidenza costo del venduto | C12: =IF('CASH FLOW'!O5=0,"",-'CASH FLOW'!O21/'CASH FLOW'!O5) | D12: Beverage, caffetteria, food e consumabili sugli incassi
B13: Incidenza manodopera completa | C13: =IF('CASH FLOW'!O5=0,"",-'CASH FLOW'!O219/'CASH FLOW'!O5) | D13: Dalla riga memo: comprende personale eventi, ritenute e contributi
B14: Incidenza commissioni su incassi | C14: =IF('CASH FLOW'!O6=0,"",-'CASH FLOW'!O177/'CASH FLOW'!O6) | D14: Pagobancomat, carte, SumUp, Axerve sui corrispettivi
B16: CASH FLOW
B17: Cash flow operativo | C17: ='CASH FLOW'!O183 | D17: Prima di fisco, investimenti e finanziamenti
B18: Cash flow operativo % | C18: =IF('CASH FLOW'!O5=0,"",'CASH FLOW'!O183/'CASH FLOW'!O5)
B19: Variazione di cassa | C19: ='CASH FLOW'!O213
B20: Cassa e banca a inizio anno | C20: ='CASH FLOW'!C214
B21: Cassa e banca a fine anno | C21: ='CASH FLOW'!N215
B23: EVENTI
B24: Ricavi eventi | C24: ='CASH FLOW'!O9
B25: Margine eventi | C25: ='CASH FLOW'!O220 | D25: Ricavi eventi meno costi diretti eventi
B26: Peso eventi sugli incassi | C26: =IF('CASH FLOW'!O5=0,"",'CASH FLOW'!O9/'CASH FLOW'!O5)
B28: TENUTA
B29: Costi di struttura mensili medi | C29: =-'CASH FLOW'!O100/12 | D29: Media dei dodici mesi
B30: Mesi di struttura coperti dalla cassa | C30: =IF(C29=0,"",C21/C29) | D30: Cassa finale diviso costi di struttura mensili
